diffusionkit/__init__.py
diffusionkit/context.py
diffusionkit/diffuse.py
diffusionkit/enhance.py
diffusionkit/image.py
diffusionkit/interfaces.py
diffusionkit/loader.py
diffusionkit/modules/__init__.py
diffusionkit/modules/attention.py
diffusionkit/modules/autoencoder.py
diffusionkit/modules/controlnet.py
diffusionkit/modules/denoisers.py
diffusionkit/modules/distributions.py
diffusionkit/modules/encoders.py
diffusionkit/modules/prompt.py
diffusionkit/modules/utils.py
diffusionkit/modules/diffusion/__init__.py
diffusionkit/modules/diffusion/ddpm.py
diffusionkit/modules/diffusion/model.py
diffusionkit/modules/diffusion/openaimodel.py
diffusionkit/modules/diffusion/util.py
diffusionkit/modules/samplers/__init__.py
diffusionkit/modules/samplers/sampler_ddim.py
diffusionkit/modules/samplers/sampler_k.py
diffusionkit-0.19.dist-info/METADATA
diffusionkit-0.19.dist-info/WHEEL
diffusionkit-0.19.dist-info/top_level.txt
diffusionkit-0.19.dist-info/RECORD
